Metadata-Version: 1.0
Name: bg-distributions
Version: 0.1
Summary: Gaussian/Binomial distributions
Home-page: UNKNOWN
Author: Francois Ferreira
Author-email: UNKNOWN
License: UNKNOWN
Platform: UNKNOWN
